<?xml version="1.0" encoding="utf-8" ?>
<dwsync>
<file name="error.php" server="82.146.34.220/g-bridge.ru/" local="130988139149276673" remote="131001027600000000" Dst="0" />
<file name="error400.php" server="82.146.34.220/g-bridge.ru/" local="130988139149351721" remote="131001027600000000" Dst="0" />
<file name="error500.php" server="82.146.34.220/g-bridge.ru/" local="130988139149952315" remote="131001027600000000" Dst="0" />
<file name="error403.php" server="82.146.34.220/g-bridge.ru/" local="130988139149722110" remote="131001027600000000" Dst="0" />
<file name="error404.php" server="82.146.34.220/g-bridge.ru/" local="130988139149822177" remote="131001027600000000" Dst="0" />
<file name="error503.php" server="82.146.34.220/g-bridge.ru/" local="130988139150032363" remote="131001027600000000" Dst="0" />
<file name="exception.php" server="82.146.34.220/g-bridge.ru/" local="130988139151547348" remote="131001027600000000" Dst="0" />
<file name="log-firebug.php" server="82.146.34.220/g-bridge.ru/" local="130988139164130044" remote="131001028200000000" Dst="0" />
<file name="log.php" server="82.146.34.220/g-bridge.ru/" local="130988139164205092" remote="131001028200000000" Dst="0" />
<file name="profile-callstack-firebug.php" server="82.146.34.220/g-bridge.ru/" local="130988139170019818" remote="131001028200000000" Dst="0" />
<file name="profile-callstack.php" server="82.146.34.220/g-bridge.ru/" local="130988139170094866" remote="131001028200000000" Dst="0" />
<file name="profile-summary-firebug.php" server="82.146.34.220/g-bridge.ru/" local="130988139170179924" remote="131001028200000000" Dst="0" />
<file name="profile-summary.php" server="82.146.34.220/g-bridge.ru/" local="130988139170255076" remote="131001028200000000" Dst="0" />
</dwsync>